bibibigtable-0.1.0.dist-info/METADATA
bibibigtable-0.1.0.dist-info/WHEEL
bibibigtable/__init__.py
bibibigtable/bigtable.py
bibibigtable/learn_datatable.py
bibibigtable-0.1.0.dist-info/RECORD
