Metadata-Version: 2.1
Name: bibibigtable
Version: 0.1.0
Summary: Big sql table or excel processing
Author-Email: Chunqi SHI <chunqishi@gmail.com>
License: MIT
Classifier: Programming Language :: Python :: 3
Classifier: License :: OSI Approved :: MIT License
Classifier: Operating System :: OS Independent
Project-URL: Homepage, https://github.com/bibiparrot/bibibigtable
Project-URL: Issues, https://github.com/bibiparrot/bibibigtable/issues
Requires-Python: >=3.10
Requires-Dist: openpyxl>=3.1.2
Requires-Dist: pandas>=2.2.2
Requires-Dist: loguru>=0.7.2
Requires-Dist: XlsxWriter>=3.2.0
Requires-Dist: python-calamine>=0.2.0
Requires-Dist: packaging>=24.0
